{
  "result": "success",
  "provider": "https://www.exchangerate-api.com",
  "documentation": "https://www.exchangerate-api.com/docs/free",
  "terms_of_use": "https://www.exchangerate-api.com/terms",
  "time_last_update_unix": 1712707351,
  "time_last_update_utc": "Wed, 10 Apr 2024 00:02:31 +0000",
  "time_next_update_unix": 1712794861,
  "time_next_update_utc": "Thu, 11 Apr 2024 00:21:01 +0000",
  "time_eol_unix": 0,
  "base_code": "NOK",
  "rates": {
    "NOK": 1,
    "AED": 0.344069,
    "AFN": 6.658141,
    "ALL": 8.80165,
    "AMD": 36.397258,
    "ANG": 0.167702,
    "AOA": 79.254114,
    "ARS": 81.016758,
    "AUD": 0.141395,
    "AWG": 0.167702,
    "AZN": 0.159019,
    "BAM": 0.168768,
    "BBD": 0.187376,
    "BDT": 10.280942,
    "BGN": 0.168762,
    "BHD": 0.035227,
    "BIF": 267.242991,
    "BMD": 0.093688,
    "BND": 0.126031,
    "BOB": 0.646448,
    "BRL": 0.470837,
    "BSD": 0.093688,
    "BTN": 7.798619,
    "BWP": 1.277802,
    "BYN": 0.305393,
    "BZD": 0.187376,
    "CAD": 0.127163,
    "CDF": 257.612613,
    "CHF": 0.084619,
    "CLP": 88.635019,
    "CNY": 0.678159,
    "COP": 351.488757,
    "CRC": 47.181901,
    "CUP": 2.248514,
    "CVE": 9.514762,
    "CZK": 2.190304,
    "DJF": 16.650337,
    "DKK": 0.643734,
    "DOP": 5.523019,
    "DZD": 12.571484,
    "EGP": 4.453321,
    "ERN": 1.405321,
    "ETB": 5.291451,
    "EUR": 0.086289,
    "FJD": 0.210461,
    "FKP": 0.073907,
    "FOK": 0.643759,
    "GBP": 0.073906,
    "GEL": 0.249996,
    "GGP": 0.073907,
    "GHS": 1.266601,
    "GIP": 0.073907,
    "GMD": 6.006973,
    "GNF": 803.675354,
    "GTQ": 0.727659,
    "GYD": 19.465623,
    "HKD": 0.733534,
    "HNL": 2.305868,
    "HRK": 0.650152,
    "HTG": 12.35739,
    "HUF": 33.631161,
    "IDR": 1483.839046,
    "ILS": 0.34644,
    "IMP": 0.073907,
    "INR": 7.798627,
    "IQD": 122.200855,
    "IRR": 3956.885691,
    "ISK": 12.977956,
    "JEP": 0.073907,
    "JMD": 14.44108,
    "JOD": 0.066425,
    "JPY": 14.216299,
    "KES": 12.173916,
    "KGS": 8.353314,
    "KHR": 376.25,
    "KID": 0.141395,
    "KMF": 42.451878,
    "KRW": 126.688394,
    "KWD": 0.028754,
    "KYD": 0.078073,
    "KZT": 41.841495,
    "LAK": 1960.644571,
    "LBP": 8385.082194,
    "LKR": 27.986269,
    "LRD": 18.116011,
    "LSL": 1.73033,
    "LYD": 0.449996,
    "MAD": 0.939196,
    "MDL": 1.651255,
    "MGA": 408.5,
    "MKD": 5.3056,
    "MMK": 246.592821,
    "MNT": 317.065658,
    "MOP": 0.755676,
    "MRU": 3.694922,
    "MUR": 4.292924,
    "MVR": 1.441079,
    "MWK": 163.644006,
    "MXN": 1.533837,
    "MYR": 0.445323,
    "MZN": 5.990247,
    "NAD": 1.73033,
    "NGN": 118.989961,
    "NIO": 3.437003,
    "NPR": 12.477791,
    "NZD": 0.154617,
    "OMR": 0.036023,
    "PAB": 0.093688,
    "PEN": 0.34564,
    "PGK": 0.354138,
    "PHP": 5.292507,
    "PKR": 26.029871,
    "PLN": 0.367744,
    "PYG": 686.549847,
    "QAR": 0.341025,
    "RON": 0.428411,
    "RSD": 10.104412,
    "RUB": 8.688464,
    "RWF": 124.509238,
    "SAR": 0.35133,
    "SBD": 0.782278,
    "SCR": 1.317834,
    "SDG": 41.622999,
    "SEK": 0.988609,
    "SGD": 0.126029,
    "SHP": 0.073907,
    "SLE": 2.1749,
    "SLL": 2175.011809,
    "SOS": 53.150558,
    "SRD": 3.263897,
    "SSP": 146.402171,
    "STN": 2.114104,
    "SYP": 1209.799727,
    "SZL": 1.73033,
    "THB": 3.40794,
    "TJS": 1.025065,
    "TMT": 0.327295,
    "TND": 0.292234,
    "TOP": 0.222819,
    "TRY": 3.019382,
    "TTD": 0.633807,
    "TVD": 0.141395,
    "TWD": 3.002383,
    "TZS": 242.463934,
    "UAH": 3.656345,
    "UGX": 356.506623,
    "USD": 0.093687,
    "UYU": 3.571229,
    "UZS": 1181.967227,
    "VES": 3.393861,
    "VND": 2332.190127,
    "VUV": 11.283101,
    "WST": 0.257594,
    "XAF": 56.602503,
    "XCD": 0.252958,
    "XDR": 0.070647,
    "XOF": 56.602503,
    "XPF": 10.297154,
    "YER": 23.406854,
    "ZAR": 1.730302,
    "ZMW": 2.319173,
    "ZWL": 1.26805
  }
}